get_jokes.py
kawhi.py
kawhi/__init__.py
kawhi/get_jokes.py
kawhi/kawhi.py
kawhi/support_modules/__init__.py
kawhi/support_modules/get_jokes.py
kawhi-0.0.47.dist-info/METADATA
kawhi-0.0.47.dist-info/WHEEL
kawhi-0.0.47.dist-info/license.txt
kawhi-0.0.47.dist-info/top_level.txt
kawhi-0.0.47.dist-info/RECORD
